pvdaq_access/__init__.py
pvdaq_access/_version.py
pvdaq_access/main.py
pvdaq_access-0.1.2.dist-info/METADATA
pvdaq_access-0.1.2.dist-info/WHEEL
pvdaq_access-0.1.2.dist-info/top_level.txt
pvdaq_access-0.1.2.dist-info/RECORD
