Metadata-Version: 2.1
Name: pvdaq_access
Version: 0.1.2
Summary: Functions to interface with PVDAQ datasets
Home-page: https://github.com/NREL/pvdaq_access
Author: Robert White
Author-email: robert.white@nrel.gov
License: BSD License (3 clause)
Keywords: photovoltaic data datasets performance power production weatherdata PVFleets SolarDataPrize
Classifier: Development Status :: 4 - Beta
Classifier: Intended Audience :: Science/Research
Classifier: License :: OSI Approved :: BSD License
Classifier: Programming Language :: Python :: 3
Classifier: Programming Language :: Python :: 3.8
Classifier: Programming Language :: Python :: 3.9
Classifier: Programming Language :: Python :: 3.10
Requires-Dist: boto3
Requires-Dist: botocore
Requires-Dist: jmespath
Requires-Dist: numpy
Requires-Dist: pandas
Requires-Dist: python-dateutil
Requires-Dist: pytz
Requires-Dist: s3transfer
Requires-Dist: six
Requires-Dist: urllib3
Requires-Dist: requests
Provides-Extra: all
Requires-Dist: ipython ; extra == 'all'
Requires-Dist: jupyter ; extra == 'all'
Requires-Dist: pytest ; extra == 'all'
Requires-Dist: pytest-cov ; extra == 'all'
Provides-Extra: doc
Requires-Dist: ipython ; extra == 'doc'
Requires-Dist: tqdm ; extra == 'doc'
